{"user":"index","panel_name":"index","view_type":"panel","disable_selection":"true","run_msec":"200","widget_width":"400","widget_height":"230","header_height":"16","content_height":"180","widgets":{"table-0":{"widgetTitle":"table 0","widgetId":"table-0","number":"0","widgetType":"table","widgetContent":{"aaData":[["Trident9","IE2","Win1"],["Trident5","IE9","Win7"],["Trident3","IE7","Win4"],["Trident8","IE1","Win7"],["Trident6","IE6","Win10"],["Trident5","IE7","Win1"],["Trident1","IE7","Win10"]],"aoColumns":[{"sTitle":"Engine"},{"sTitle":"Browser"},{"sTitle":"Platform"}]},"pos":"1","width":"400","height":"230","header_height":"16","content_height":"180"},"slide-0":{"widgetTitle":"slide 0","widgetId":"slide-0","number":"0","widgetType":"slide","widgetContent":"<iframe src=\"http:\/\/www.slideshare.net\/slideshow\/embed_code\/16073451\" width=\"427\" height=\"356\" frameborder=\"0\" marginwidth=\"0\" marginheight=\"0\" scrolling=\"no\" style=\"border:1px solid #CCC;border-width:1px 1px 0;margin-bottom:5px\" allowfullscreen webkitallowfullscreen mozallowfullscreen> <\/iframe> <div style=\"margin-bottom:5px\"> <strong> <a href=\"https:\/\/www.slideshare.net\/narrendar\/ros-an-opensource-robotic-framework\" title=\"ROS - An Opensource Robotic Framework\" target=\"_blank\">ROS - An Opensource Robotic Framework<\/a> <\/strong> from <strong><a href=\"http:\/\/www.slideshare.net\/narrendar\" target=\"_blank\">Narrendar Narren<\/a><\/strong> <\/div>","pos":"2","width":"700","height":"530","header_height":"16","content_height":"480"},"text-0":{"widgetTitle":"text 0","widgetId":"text-0","number":"0","widgetType":"text","widgetContent":"I am a text widget ^_^","pos":"0","width":"800","height":"230","header_height":"16","content_height":"180"}}}
